<entities anm2root="gfx/" version="5">

    <!--MINISTRO VARIANTS-->
    <entity name="Culo"
        id="305" variant="30" anm2path="culo.anm2" baseHP="12" stageHP="2" boss="0"
            collisionDamage="1" collisionMass="6" collisionRadius="9" numGridCollisionPoints="12" shadowSize="12" friction="1" reroll="true" champion="0"
            bestiary="true" portrait="85" bestiaryTransform="0,0,1" bestiaryAnim="Idle">
        <gibs amount="5" blood="0" bone="0" eye="0" gut="0" large="0" poop="1" />
        <preload-snd id="485" /> <!-- SOUND_CLAP -->
    </entity>


    <!--HOARD ENEMIES-->
    <!--Acme and Acme's Anvil-->
    <entity id="10" variant="30" name="Acme" reroll="true" baseHP="10" stageHP="2" boss="0" champion="0" collisionDamage="1" collisionMass="5" collisionRadius="13" friction="1" numGridCollisionPoints="12" shadowSize="6" portrait="85" anm2path="acme.anm2" bestiary="true" bestiaryTransform="0,0,1" bestiaryAnim="Head">
        <gibs amount="6" blood="1" bone="1" eye="1" gut="1" large="0" poop="0" />
    </entity>
    <entity id="1000" variant="62" anm2path="effect_Anvil.anm2" baseHP="0" boss="0" champion="0" collisionDamage="0" collisionMass="0" collisionRadius="0" friction="1" name="Acme's Anvil" numGridCollisionPoints="0" shadowSize="14" stageHP="0">
        <gibs amount="0" blood="0" bone="0" eye="0" gut="0" large="0" />
    </entity>
    <!--Skooter and Super Skooter -->
    <entity id="666" variant="63" subtype="1" name="Skooter" reroll="true" baseHP="5" stageHP="1" boss="0" champion="0" collisionDamage="1" collisionMass="5" collisionRadius="13" friction="1" numGridCollisionPoints="12" shadowSize="11" portrait="646" anm2path="skooter.anm2" bestiary="true" bestiaryTransform="0,0,1" bestiaryAnim="idle">
        <gibs amount="0" blood="0" bone="0" eye="0" gut="0" large="0" poop="0" worm="0" />
	</entity>
    <!--Super Skooter-->
    <entity id="666" variant="64" subtype="2" name="Super Skooter" reroll="true" baseHP="5" stageHP="1" boss="0" champion="0" collisionDamage="1" collisionMass="5" collisionRadius="13" friction="1" numGridCollisionPoints="12" shadowSize="11" portrait="646" anm2path="super_skooter.anm2" bestiary="true" bestiaryTransform="0,0,1" bestiaryAnim="idle">
        <gibs amount="0" blood="0" bone="0" eye="0" gut="0" large="0" poop="0" worm="0" />
	</entity> 
    <!--Desirer-->
    <entity anm2path="desirer.anm2" baseHP="65" boss="0" champion="0" collisionDamage="1" collisionMass="30" collisionRadius="13" friction="1" id="86" name="Desirer" numGridCollisionPoints="12" portrait="54" reroll="true" shadowSize="17" stageHP="0" variant="853983151">
        <gibs amount="6" blood="1" bone="1" eye="0" gut="1" large="0" worm="1"/>
	</entity>
    <!--Sleazebag-->
    <entity anm2path="sleazebag.anm2" baseHP="20" boss="0" champion="0" collisionDamage="0" collisionMass="7" collisionRadius="13" friction="1" id="22" variant="853983" name="Sleazebag" numGridCollisionPoints="12" portrait="15" reroll="true" shadowSize="14" stageHP="0">
        <gibs amount="6" blood="1" bone="1" eye="0" gut="1" large="0"/>
	</entity>
    <!--Humbled-->
    <entity anm2path="humbled.anm2" baseHP="6" shieldStrength="3" boss="0" champion="0" collisionDamage="1" collisionMass="5" collisionRadius="13" friction="1" id="884" variant="853983151" name="Humbled" numGridCollisionPoints="12" portrait="318" reroll="true" shadowSize="11" stageHP="0.2">
        <gibs amount="0" blood="0" bone="0" eye="0" gut="0" large="0"/>
	</entity>

</entities>